extratools_html/__init__.py
extratools_html/cleanup.py
extratools_html/py.typed
extratools_html-0.1.18.dist-info/METADATA
extratools_html-0.1.18.dist-info/WHEEL
extratools_html-0.1.18.dist-info/licenses/LICENSE
extratools_html-0.1.18.dist-info/RECORD
