Metadata-Version: 2.4
Name: extratools-html
Version: 0.1.18
Project-URL: Repository, https://github.com/chuanconggao/extratools-html
Author-email: Chuancong Gao <chuanconggao@users.noreply.github.com>
License-Expression: MIT
License-File: LICENSE
Requires-Python: >=3.12
Requires-Dist: backoff>=2.2.1
Requires-Dist: blob-dict>=0.1.11
Requires-Dist: html2text>=2024.2.26
Requires-Dist: httpx>=0.28.1
Requires-Dist: minify-html>=0.16.4
Requires-Dist: truststore>=0.10.1
Provides-Extra: browser
Requires-Dist: playwright>=1.51.0; extra == 'browser'
